pyqt_no_signal_widget/__init__.py
pyqt_no_signal_widget/no_signal_widget.py
pyqt_no_signal_widget-0.1.0.dist-info/METADATA
pyqt_no_signal_widget-0.1.0.dist-info/WHEEL
pyqt_no_signal_widget-0.1.0.dist-info/top_level.txt
pyqt_no_signal_widget-0.1.0.dist-info/RECORD
