Metadata-Version: 2.4
Name: pyqt-no-signal-widget
Version: 0.1.0
Summary: A customizable PyQt6 widget displaying a retro 'No Signal' TV animation.
Author-email: PNKgeekPDX <pinkgeekportland@gmail.com>
Project-URL: Homepage, https://github.com/PNKgeekPDX/pyqt-no-signal-widget
Project-URL: Issues, https://github.com/PNKgeekPDX/pyqt-no-signal-widget/issues
Keywords: pyqt,pyqt6,widget,custom widget,animation,no signal,gui,qwebengine,retro,tv
Classifier: Development Status :: 3 - Alpha
Classifier: Intended Audience :: Developers
Classifier: License :: OSI Approved :: MIT License
Classifier: Operating System :: OS Independent
Classifier: Programming Language :: Python :: 3
Classifier: Programming Language :: Python :: 3.8
Classifier: Programming Language :: Python :: 3.9
Classifier: Programming Language :: Python :: 3.10
Classifier: Programming Language :: Python :: 3.11
Classifier: Programming Language :: Python :: 3.12
Classifier: Topic :: Software Development :: Libraries :: Python Modules
Classifier: Topic :: Software Development :: User Interfaces
Classifier: Environment :: X11 Applications :: Qt
Classifier: Environment :: MacOS X :: Cocoa
Classifier: Environment :: Win32 (MS Windows)
Requires-Python: >=3.8
Requires-Dist: PyQt6<7.0.0,>=6.4.0
Requires-Dist: PyQt6-WebEngine<7.0.0,>=6.4.0
